---
title: PC in JVM
date: 2019-12-28 21:48:36
tags: jvm
---

[PC(Program Counter Register)](https://docs.oracle.com/javase/specs/jvms/se11/html/jvms-2.html#jvms-2.5.2): The Java Virtual Machine can support many threads of execution at once (JLS §17). Each Java Virtual Machine thread has its **own pc** (program counter) register. At any point, each Java Virtual Machine thread is executing the code of **a single method**, namely the **current method** (§2.6) for that thread. If that method is not native, the pc register contains the address of the Java Virtual Machine instruction currently being executed. If the method currently being executed by the thread is native, the value of the Java Virtual Machine's pc register is undefined. The Java Virtual Machine's pc register is wide enough to hold a returnAddress or a native pointer on the specific platform.

<!--more-->

从上面的说明中可以提炼出一下几点信息：

1. 程序计数器是线程私有的
2. 程序计数器指向的是当前线程中正在被执行方法的地址(行号)
3. 如果执行的本地方法，则计数器值为`undefined`

```java
public static int add(int, int);
  descriptor: (II)I
  flags: (0x0009) ACC_PUBLIC, ACC_STATIC
  Code:
    stack=2, locals=2, args_size=2
        0: getstatic     #2                  // Field java/lang/System.out:Ljava/io/PrintStream;
        3: ldc           #3                  // String method add...
        5: invokevirtual #4                  // Method java/io/PrintStream.println:(Ljava/lang/String;)V
        8: iload_0
        9: iload_1
        10: iadd
        11: ireturn

public static int sub();
  descriptor: ()I
  flags: (0x0009) ACC_PUBLIC, ACC_STATIC
  Code:
    stack=2, locals=2, args_size=0
        0: getstatic     #2                  // Field java/lang/System.out:Ljava/io/PrintStream;
        3: ldc           #5                  // String method sub...
        5: invokevirtual #4                  // Method java/io/PrintStream.println:(Ljava/lang/String;)V
        8: iconst_1
        9: istore_0
        10: iconst_2
        11: istore_1
        12: iload_0
        13: iload_1
        14: invokestatic  #6                  // Method add:(II)I
        17: pop
        18: iload_0
        19: iload_1
        20: isub
        21: ireturn
```

如上代码段，可以简单理解`PC`中存储的是每条`jvm`指令开头的数字。

### 特定

此内存区域是唯一一个在`Java`虚拟机规范中没有规定任何`OutOfMemoryError`情况的区域。

### 参考

1. [The Java® Virtual Machine Specification](https://docs.oracle.com/javase/specs/jvms/se11/html/index.html)
2. 周志明. (2014). 深入理解 Java 虚拟机一 JVM 高级特性与最佳实践.
